hyo2.abc-0.4.2-py3.8-nspkg.pth
hyo2/abc/__init__.py
hyo2/abc/app/__init__.py
hyo2/abc/app/app_info.py
hyo2/abc/app/app_style.py
hyo2/abc/app/qt_progress.py
hyo2/abc/app/report.py
hyo2/abc/app/web_renderer.py
hyo2/abc/app/dialogs/__init__.py
hyo2/abc/app/dialogs/about/__init__.py
hyo2/abc/app/dialogs/about/about_dialog.py
hyo2/abc/app/dialogs/about/tabs/__init__.py
hyo2/abc/app/dialogs/about/tabs/gdal_info.py
hyo2/abc/app/dialogs/about/tabs/general_info.py
hyo2/abc/app/dialogs/about/tabs/license.py
hyo2/abc/app/dialogs/about/tabs/local_environment.py
hyo2/abc/app/dialogs/exception/__init__.py
hyo2/abc/app/dialogs/exception/exception_dialog.py
hyo2/abc/app/dialogs/exception/media/bug.png
hyo2/abc/app/dialogs/noaa_s57/__init__.py
hyo2/abc/app/dialogs/noaa_s57/__main__.py
hyo2/abc/app/dialogs/noaa_s57/noaa_s57.py
hyo2/abc/app/dialogs/noaa_s57/noaa_support.py
hyo2/abc/app/dialogs/noaa_s57/media/Caris_Support_Files_2019v0.zip
hyo2/abc/app/dialogs/noaa_s57/media/Caris_Support_Files_2019v1.zip
hyo2/abc/app/dialogs/noaa_s57/media/Caris_Support_Files_2019v2.zip
hyo2/abc/app/dialogs/noaa_s57/media/Caris_Support_Files_2019v3.zip
hyo2/abc/app/dialogs/noaa_s57/media/Caris_Support_Files_2019v4.zip
hyo2/abc/app/dialogs/noaa_s57/media/Caris_Support_Files_2020v1.zip
hyo2/abc/app/dialogs/noaa_s57/media/Caris_Support_Files_2020v3.zip
hyo2/abc/app/dialogs/noaa_s57/media/Caris_Support_Files_2021v1.zip
hyo2/abc/app/dialogs/noaa_s57/media/Caris_Support_Files_2022v1.zip
hyo2/abc/app/dialogs/noaa_s57/media/Caris_Support_Files_2022v2.zip
hyo2/abc/app/dialogs/noaa_s57/media/noaa_support.png
hyo2/abc/app/dialogs/noaa_s57/media/small_info.png
hyo2/abc/app/media/LICENSE
hyo2/abc/app/media/app.css
hyo2/abc/app/media/app_icon.png
hyo2/abc/app/media/html.css
hyo2/abc/app/media/manual.pdf
hyo2/abc/app/media/noaa_support.png
hyo2/abc/app/media/poweredby.png
hyo2/abc/app/media/rc/branch_closed-on.png
hyo2/abc/app/media/rc/branch_closed.png
hyo2/abc/app/media/rc/branch_open-on.png
hyo2.abc-0.4.2.dist-info/AUTHORS.rst
hyo2.abc-0.4.2.dist-info/LICENSE
hyo2.abc-0.4.2.dist-info/METADATA
hyo2.abc-0.4.2.dist-info/WHEEL
hyo2.abc-0.4.2.dist-info/namespace_packages.txt
hyo2.abc-0.4.2.dist-info/top_level.txt
hyo2.abc-0.4.2.dist-info/RECORD
