Metadata-Version: 2.1
Name: hyo2.abc
Version: 0.4.2
Summary: Common elements for HydrOffice libraries and applications.
Home-page: https://www.hydroffice.org
Author: Giuseppe Masetti
Author-email: gmasetti@ccom.unh.edu
License: LGPLv3 license
Keywords: hydrography ocean mapping
Platform: UNKNOWN
Classifier: Development Status :: 5 - Production/Stable
Classifier: Intended Audience :: Science/Research
Classifier: Natural Language :: English
Classifier: License :: OSI Approved :: GNU Lesser General Public License v3 (LGPLv3)
Classifier: Operating System :: OS Independent
Classifier: Programming Language :: Python
Classifier: Programming Language :: Python :: 3
Classifier: Programming Language :: Python :: 3.6
Classifier: Programming Language :: Python :: 3.7
Classifier: Programming Language :: Python :: 3.8
Classifier: Programming Language :: Python :: 3.9
Classifier: Topic :: Scientific/Engineering :: GIS
Requires-Python: >=3.5
License-File: LICENSE
License-File: AUTHORS.rst
Requires-Dist: appdirs
Requires-Dist: gdal
Requires-Dist: pyproj
Requires-Dist: numpy
Requires-Dist: requests
Provides-Extra: extended
Requires-Dist: bidict ; extra == 'extended'
Requires-Dist: matplotlib ; extra == 'extended'
Requires-Dist: psutil ; extra == 'extended'
Requires-Dist: PySide2 ; extra == 'extended'
Requires-Dist: pywin32 ; (platform_system == "Windows") and extra == 'extended'
